{"rooms":[{"referenceID":"5406d99c-c8f8-4771-a15b-3bffe1ef938d","position":{"x":170.0,"y":102.0,"z":-0.10999999940395355},"rotation":{"x":0.0,"y":0.0,"z":0.0,"w":1.0},"floor":1,"objectName":"","variationIndex":0,"objectSize":0,"objectQuality":0,"isActivated":true,"shouldBeActivated":true,"isInside":true,"isBuilt":true,"isMarkedForDemolish":false,"constructionInProgress":false,"deconstructionInProgress":false,"constructionEnergyAdded":1.0,"isPlanned":false,"condition":1.0,"isBroken":false,"isBeingRepaired":false,"cleanliness":1.0,"colors":[],"roomType":2,"businessReferenceID":"","allowAllBusinessesOfType":false,"attachedCountersReferenceIDs":[],"connectedCargoBayReferenceID":"","roomStartPos":{"x":163.0,"y":104.0},"roomEndPos":{"x":177.0,"y":100.0},"roomSize":{"x":15.0,"y":5.0},"allowedPerson":0,"allowedGender":1,"allowedWealthClass":0,"allowedEmployeeTypes":[],"hasCreatedJobTasks":false,"timeToRegenerateJobTasksString":"0001-01-01 20:07","nbrOfStationedEmployees":-1},{"referenceID":"9f2b831d-8d61-4c12-86b7-f2007b256be9","position":{"x":170.0,"y":108.0,"z":-0.10999999940395355},"rotation":{"x":0.0,"y":0.0,"z":0.0,"w":1.0},"floor":1,"objectName":"","variationIndex":0,"objectSize":0,"objectQuality":0,"isActivated":true,"shouldBeActivated":true,"isInside":true,"isBuilt":true,"isMarkedForDemolish":false,"constructionInProgress":false,"deconstructionInProgress":false,"constructionEnergyAdded":1.0,"isPlanned":false,"condition":1.0,"isBroken":false,"isBeingRepaired":false,"cleanliness":1.0,"colors":[],"roomType":2,"businessReferenceID":"","allowAllBusinessesOfType":false,"attachedCountersReferenceIDs":[],"connectedCargoBayReferenceID":"","roomStartPos":{"x":163.0,"y":110.0},"roomEndPos":{"x":177.0,"y":106.0},"roomSize":{"x":15.0,"y":5.0},"allowedPerson":0,"allowedGender":2,"allowedWealthClass":0,"allowedEmployeeTypes":[],"hasCreatedJobTasks":false,"timeToRegenerateJobTasksString":"0001-01-01 20:07","nbrOfStationedEmployees":-1},{"referenceID":"2d254123-c4bb-4731-9cc8-0237701e1cb8","position":{"x":378.5,"y":142.0,"z":0.0},"rotation":{"x":0.0,"y":0.0,"z":0.0,"w":1.0},"floor":-1,"objectName":"","variationIndex":0,"objectSize":0,"objectQuality":0,"isActivated":true,"shouldBeActivated":true,"isInside":true,"isBuilt":true,"isMarkedForDemolish":false,"constructionInProgress":false,"deconstructionInProgress":false,"constructionEnergyAdded":1.0,"isPlanned":false,"condition":1.0,"isBroken":false,"isBeingRepaired":false,"cleanliness":1.0,"colors":[],"roomType":2,"businessReferenceID":"","allowAllBusinessesOfType":false,"attachedCountersReferenceIDs":[],"connectedCargoBayReferenceID":"","roomStartPos":{"x":376.0,"y":144.0},"roomEndPos":{"x":381.0,"y":140.0},"roomSize":{"x":6.0,"y":5.0},"allowedPerson":0,"allowedGender":2,"allowedWealthClass":0,"allowedEmployeeTypes":[],"hasCreatedJobTasks":false,"timeToRegenerateJobTasksString":"0001-01-01 20:07","nbrOfStationedEmployees":-1},{"referenceID":"e68b403e-50c1-4f09-9962-af3eeae06900","position":{"x":384.0,"y":142.0,"z":0.0},"rotation":{"x":0.0,"y":0.0,"z":0.0,"w":1.0},"floor":-1,"objectName":"","variationIndex":0,"objectSize":0,"objectQuality":0,"isActivated":true,"shouldBeActivated":true,"isInside":true,"isBuilt":true,"isMarkedForDemolish":false,"constructionInProgress":false,"deconstructionInProgress":false,"constructionEnergyAdded":1.0,"isPlanned":false,"condition":1.0,"isBroken":false,"isBeingRepaired":false,"cleanliness":1.0,"colors":[],"roomType":2,"businessReferenceID":"","allowAllBusinessesOfType":false,"attachedCountersReferenceIDs":[],"connectedCargoBayReferenceID":"","roomStartPos":{"x":382.0,"y":144.0},"roomEndPos":{"x":386.0,"y":140.0},"roomSize":{"x":5.0,"y":5.0},"allowedPerson":0,"allowedGender":1,"allowedWealthClass":0,"allowedEmployeeTypes":[],"hasCreatedJobTasks":false,"timeToRegenerateJobTasksString":"0001-01-01 20:07","nbrOfStationedEmployees":-1},{"referenceID":"16732476-7c15-4238-820d-0547b40d9704","position":{"x":389.5,"y":240.5,"z":-0.10999999940395355},"rotation":{"x":0.0,"y":0.0,"z":0.0,"w":1.0},"floor":1,"objectName":"","variationIndex":0,"objectSize":0,"objectQuality":0,"isActivated":true,"shouldBeActivated":true,"isInside":true,"isBuilt":true,"isMarkedForDemolish":false,"constructionInProgress":false,"deconstructionInProgress":false,"constructionEnergyAdded":1.0,"isPlanned":false,"condition":1.0,"isBroken":false,"isBeingRepaired":false,"cleanliness":1.0,"colors":[],"roomType":2,"businessReferenceID":"","allowAllBusinessesOfType":false,"attachedCountersReferenceIDs":[],"connectedCargoBayReferenceID":"","roomStartPos":{"x":387.0,"y":246.0},"roomEndPos":{"x":392.0,"y":235.0},"roomSize":{"x":6.0,"y":12.0},"allowedPerson":0,"allowedGender":2,"allowedWealthClass":0,"allowedEmployeeTypes":[],"hasCreatedJobTasks":false,"timeToRegenerateJobTasksString":"0001-01-02 20:47","nbrOfStationedEmployees":-1},{"referenceID":"70254cc7-9f2b-4172-8665-96f6b467435b","position":{"x":389.5,"y":228.5,"z":-0.10999999940395355},"rotation":{"x":0.0,"y":0.0,"z":0.0,"w":1.0},"floor":1,"objectName":"","variationIndex":0,"objectSize":0,"objectQuality":0,"isActivated":true,"shouldBeActivated":true,"isInside":true,"isBuilt":true,"isMarkedForDemolish":false,"constructionInProgress":false,"deconstructionInProgress":false,"constructionEnergyAdded":1.0,"isPlanned":false,"condition":1.0,"isBroken":false,"isBeingRepaired":false,"cleanliness":1.0,"colors":[],"roomType":2,"businessReferenceID":"","allowAllBusinessesOfType":false,"attachedCountersReferenceIDs":[],"connectedCargoBayReferenceID":"","roomStartPos":{"x":387.0,"y":234.0},"roomEndPos":{"x":392.0,"y":223.0},"roomSize":{"x":6.0,"y":12.0},"allowedPerson":0,"allowedGender":1,"allowedWealthClass":0,"allowedEmployeeTypes":[],"hasCreatedJobTasks":false,"timeToRegenerateJobTasksString":"0001-01-02 20:50","nbrOfStationedEmployees":-1},{"referenceID":"503e1692-b40a-4d62-968c-5fb91d9b4fbf","position":{"x":384.0,"y":104.5,"z":-0.10999999940395355},"rotation":{"x":0.0,"y":0.0,"z":0.0,"w":1.0},"floor":1,"objectName":"","variationIndex":0,"objectSize":0,"objectQuality":0,"isActivated":true,"shouldBeActivated":true,"isInside":true,"isBuilt":true,"isMarkedForDemolish":false,"constructionInProgress":false,"deconstructionInProgress":false,"constructionEnergyAdded":1.0,"isPlanned":false,"condition":1.0,"isBroken":false,"isBeingRepaired":false,"cleanliness":1.0,"colors":[],"roomType":2,"businessReferenceID":"","allowAllBusinessesOfType":false,"attachedCountersReferenceIDs":[],"connectedCargoBayReferenceID":"","roomStartPos":{"x":379.0,"y":107.0},"roomEndPos":{"x":389.0,"y":102.0},"roomSize":{"x":11.0,"y":6.0},"allowedPerson":0,"allowedGender":1,"allowedWealthClass":0,"allowedEmployeeTypes":[],"hasCreatedJobTasks":false,"timeToRegenerateJobTasksString":"0001-01-02 23:46","nbrOfStationedEmployees":-1},{"referenceID":"b5721947-9cd8-445d-b84a-83b76a5a88c9","position":{"x":396.5,"y":104.5,"z":-0.10999999940395355},"rotation":{"x":0.0,"y":0.0,"z":0.0,"w":1.0},"floor":1,"objectName":"","variationIndex":0,"objectSize":0,"objectQuality":0,"isActivated":true,"shouldBeActivated":true,"isInside":true,"isBuilt":true,"isMarkedForDemolish":false,"constructionInProgress":false,"deconstructionInProgress":false,"constructionEnergyAdded":1.0,"isPlanned":false,"condition":1.0,"isBroken":false,"isBeingRepaired":false,"cleanliness":1.0,"colors":[],"roomType":2,"businessReferenceID":"","allowAllBusinessesOfType":false,"attachedCountersReferenceIDs":[],"connectedCargoBayReferenceID":"","roomStartPos":{"x":391.0,"y":107.0},"roomEndPos":{"x":402.0,"y":102.0},"roomSize":{"x":12.0,"y":6.0},"allowedPerson":0,"allowedGender":2,"allowedWealthClass":0,"allowedEmployeeTypes":[],"hasCreatedJobTasks":false,"timeToRegenerateJobTasksString":"0001-01-02 23:49","nbrOfStationedEmployees":-1},{"referenceID":"b659822e-9aa1-42b8-8636-cc2a59a8ab21","position":{"x":360.5,"y":122.0,"z":-0.10999999940395355},"rotation":{"x":0.0,"y":0.0,"z":0.0,"w":1.0},"floor":2,"objectName":"","variationIndex":0,"objectSize":0,"objectQuality":0,"isActivated":true,"shouldBeActivated":true,"isInside":true,"isBuilt":true,"isMarkedForDemolish":false,"constructionInProgress":false,"deconstructionInProgress":false,"constructionEnergyAdded":1.0,"isPlanned":false,"condition":1.0,"isBroken":false,"isBeingRepaired":false,"cleanliness":1.0,"colors":[],"roomType":0,"businessReferenceID":"","allowAllBusinessesOfType":false,"attachedCountersReferenceIDs":[],"connectedCargoBayReferenceID":"","roomStartPos":{"x":351.0,"y":125.0},"roomEndPos":{"x":370.0,"y":119.0},"roomSize":{"x":20.0,"y":7.0},"allowedPerson":2,"allowedGender":0,"allowedWealthClass":0,"allowedEmployeeTypes":[0,1,2,3,4,5,6,7,8,9,10,11,12,13,14,15,16,17,18,19],"hasCreatedJobTasks":false,"timeToRegenerateJobTasksString":"0001-01-03 03:53","nbrOfStationedEmployees":-1},{"referenceID":"e83ea6c4-8d84-4966-9dfe-110ff2b319a5","position":{"x":442.5,"y":91.0,"z":0.0},"rotation":{"x":0.0,"y":0.0,"z":0.0,"w":1.0},"floor":0,"objectName":"","variationIndex":0,"objectSize":0,"objectQuality":0,"isActivated":false,"shouldBeActivated":false,"isInside":true,"isBuilt":true,"isMarkedForDemolish":false,"constructionInProgress":false,"deconstructionInProgress":false,"constructionEnergyAdded":1.0,"isPlanned":false,"condition":1.0,"isBroken":false,"isBeingRepaired":false,"cleanliness":1.0,"colors":[],"roomType":4,"businessReferenceID":"","allowAllBusinessesOfType":false,"attachedCountersReferenceIDs":[],"connectedCargoBayReferenceID":"","roomStartPos":{"x":431.0,"y":94.0},"roomEndPos":{"x":454.0,"y":88.0},"roomSize":{"x":24.0,"y":7.0},"allowedPerson":0,"allowedGender":0,"allowedWealthClass":0,"allowedEmployeeTypes":[],"hasCreatedJobTasks":false,"timeToRegenerateJobTasksString":"0001-01-03 07:30","nbrOfStationedEmployees":-1},{"referenceID":"d761f58d-a7e3-4550-b392-f2d3cc3c6d7b","position":{"x":464.5,"y":91.0,"z":0.0},"rotation":{"x":0.0,"y":0.0,"z":0.0,"w":1.0},"floor":0,"objectName":"","variationIndex":0,"objectSize":0,"objectQuality":0,"isActivated":false,"shouldBeActivated":false,"isInside":true,"isBuilt":true,"isMarkedForDemolish":false,"constructionInProgress":false,"deconstructionInProgress":false,"constructionEnergyAdded":1.0,"isPlanned":false,"condition":1.0,"isBroken":false,"isBeingRepaired":false,"cleanliness":1.0,"colors":[],"roomType":4,"businessReferenceID":"","allowAllBusinessesOfType":false,"attachedCountersReferenceIDs":[],"connectedCargoBayReferenceID":"","roomStartPos":{"x":455.0,"y":94.0},"roomEndPos":{"x":474.0,"y":88.0},"roomSize":{"x":20.0,"y":7.0},"allowedPerson":0,"allowedGender":0,"allowedWealthClass":0,"allowedEmployeeTypes":[],"hasCreatedJobTasks":false,"timeToRegenerateJobTasksString":"0001-01-03 07:30","nbrOfStationedEmployees":-1},{"referenceID":"ffac9802-8ea5-45a6-aa63-bce728b09e19","position":{"x":492.5,"y":91.0,"z":0.0},"rotation":{"x":0.0,"y":0.0,"z":0.0,"w":1.0},"floor":0,"objectName":"","variationIndex":0,"objectSize":0,"objectQuality":0,"isActivated":false,"shouldBeActivated":false,"isInside":true,"isBuilt":true,"isMarkedForDemolish":false,"constructionInProgress":false,"deconstructionInProgress":false,"constructionEnergyAdded":1.0,"isPlanned":false,"condition":1.0,"isBroken":false,"isBeingRepaired":false,"cleanliness":1.0,"colors":[],"roomType":4,"businessReferenceID":"","allowAllBusinessesOfType":false,"attachedCountersReferenceIDs":[],"connectedCargoBayReferenceID":"","roomStartPos":{"x":475.0,"y":94.0},"roomEndPos":{"x":510.0,"y":88.0},"roomSize":{"x":36.0,"y":7.0},"allowedPerson":0,"allowedGender":0,"allowedWealthClass":0,"allowedEmployeeTypes":[],"hasCreatedJobTasks":false,"timeToRegenerateJobTasksString":"0001-01-03 07:30","nbrOfStationedEmployees":-1},{"referenceID":"5540a83f-8278-4b0e-b34a-ebefede441ac","position":{"x":384.0,"y":91.0,"z":-0.10999999940395355},"rotation":{"x":0.0,"y":0.0,"z":0.0,"w":1.0},"floor":2,"objectName":"","variationIndex":0,"objectSize":0,"objectQuality":0,"isActivated":true,"shouldBeActivated":true,"isInside":true,"isBuilt":true,"isMarkedForDemolish":false,"constructionInProgress":false,"deconstructionInProgress":false,"constructionEnergyAdded":1.0,"isPlanned":false,"condition":1.0,"isBroken":false,"isBeingRepaired":false,"cleanliness":1.0,"colors":[],"roomType":2,"businessReferenceID":"","allowAllBusinessesOfType":false,"attachedCountersReferenceIDs":[],"connectedCargoBayReferenceID":"","roomStartPos":{"x":379.0,"y":94.0},"roomEndPos":{"x":389.0,"y":88.0},"roomSize":{"x":11.0,"y":7.0},"allowedPerson":0,"allowedGender":1,"allowedWealthClass":0,"allowedEmployeeTypes":[],"hasCreatedJobTasks":false,"timeToRegenerateJobTasksString":"0001-01-04 00:55","nbrOfStationedEmployees":-1},{"referenceID":"b7dbbe7d-e27c-4412-9d30-178df862639b","position":{"x":396.5,"y":91.0,"z":-0.10999999940395355},"rotation":{"x":0.0,"y":0.0,"z":0.0,"w":1.0},"floor":2,"objectName":"","variationIndex":0,"objectSize":0,"objectQuality":0,"isActivated":true,"shouldBeActivated":true,"isInside":true,"isBuilt":true,"isMarkedForDemolish":false,"constructionInProgress":false,"deconstructionInProgress":false,"constructionEnergyAdded":1.0,"isPlanned":false,"condition":1.0,"isBroken":false,"isBeingRepaired":false,"cleanliness":1.0,"colors":[],"roomType":2,"businessReferenceID":"","allowAllBusinessesOfType":false,"attachedCountersReferenceIDs":[],"connectedCargoBayReferenceID":"","roomStartPos":{"x":391.0,"y":94.0},"roomEndPos":{"x":402.0,"y":88.0},"roomSize":{"x":12.0,"y":7.0},"allowedPerson":0,"allowedGender":2,"allowedWealthClass":0,"allowedEmployeeTypes":[],"hasCreatedJobTasks":false,"timeToRegenerateJobTasksString":"0001-01-04 00:56","nbrOfStationedEmployees":-1},{"referenceID":"7810334a-b8f8-4265-a227-57e4f503626e","position":{"x":122.0,"y":121.0,"z":-0.10999999940395355},"rotation":{"x":0.0,"y":0.0,"z":0.0,"w":1.0},"floor":1,"objectName":"Valentino","variationIndex":0,"objectSize":0,"objectQuality":0,"isActivated":true,"shouldBeActivated":true,"isInside":true,"isBuilt":true,"isMarkedForDemolish":false,"constructionInProgress":false,"deconstructionInProgress":false,"constructionEnergyAdded":1.0,"isPlanned":false,"condition":1.0,"isBroken":false,"isBeingRepaired":false,"cleanliness":1.0,"colors":[],"roomType":3,"businessReferenceID":"804b422c-0a01-4d8f-9572-c87096dc0368","allowAllBusinessesOfType":false,"attachedCountersReferenceIDs":["4917051c-4ce8-42ac-ab26-0e03e3adc963","a19a3170-a05a-4995-9620-81b173e707fa","1240db1b-e483-44c7-927c-b410a8b467bf","71c7bac4-6c5c-40b1-a805-44e051fb18dc"],"connectedCargoBayReferenceID":"","roomStartPos":{"x":114.0,"y":125.0},"roomEndPos":{"x":130.0,"y":117.0},"roomSize":{"x":17.0,"y":9.0},"allowedPerson":0,"allowedGender":0,"allowedWealthClass":0,"allowedEmployeeTypes":[],"hasCreatedJobTasks":false,"timeToRegenerateJobTasksString":"0001-01-08 15:10","nbrOfStationedEmployees":-1}],"baggageClaims":[{"referenceID":"decf2c74-e0ca-4ec8-bb15-bc6c2b0455cc","position":{"x":442.5,"y":117.5,"z":0.0},"rotation":{"x":0.0,"y":0.0,"z":0.0,"w":1.0},"floor":0,"objectName":"","variationIndex":0,"objectSize":0,"objectQuality":0,"isActivated":true,"shouldBeActivated":true,"isInside":true,"isBuilt":true,"isMarkedForDemolish":false,"constructionInProgress":false,"deconstructionInProgress":false,"constructionEnergyAdded":1.0,"isPlanned":false,"condition":1.0,"isBroken":false,"isBeingRepaired":false,"cleanliness":1.0,"colors":[],"roomType":6,"businessReferenceID":"","allowAllBusinessesOfType":false,"attachedCountersReferenceIDs":[],"connectedCargoBayReferenceID":"","roomStartPos":{"x":435.0,"y":124.0},"roomEndPos":{"x":450.0,"y":111.0},"roomSize":{"x":16.0,"y":14.0},"allowedPerson":0,"allowedGender":0,"allowedWealthClass":0,"allowedEmployeeTypes":[],"hasCreatedJobTasks":false,"timeToRegenerateJobTasksString":"0001-01-01 20:07","nbrOfStationedEmployees":-1,"connectedCargoBayReferenceIDNew":"a721f8f9-5eab-443d-8286-c062d420f0eb"},{"referenceID":"2421a456-0d06-44a5-b072-1d339a754d5b","position":{"x":458.5,"y":117.5,"z":0.0},"rotation":{"x":0.0,"y":0.0,"z":0.0,"w":1.0},"floor":0,"objectName":"","variationIndex":0,"objectSize":0,"objectQuality":0,"isActivated":true,"shouldBeActivated":true,"isInside":true,"isBuilt":true,"isMarkedForDemolish":false,"constructionInProgress":false,"deconstructionInProgress":false,"constructionEnergyAdded":1.0,"isPlanned":false,"condition":1.0,"isBroken":false,"isBeingRepaired":false,"cleanliness":1.0,"colors":[],"roomType":6,"businessReferenceID":"","allowAllBusinessesOfType":false,"attachedCountersReferenceIDs":[],"connectedCargoBayReferenceID":"","roomStartPos":{"x":451.0,"y":124.0},"roomEndPos":{"x":466.0,"y":111.0},"roomSize":{"x":16.0,"y":14.0},"allowedPerson":0,"allowedGender":0,"allowedWealthClass":0,"allowedEmployeeTypes":[],"hasCreatedJobTasks":false,"timeToRegenerateJobTasksString":"0001-01-01 20:07","nbrOfStationedEmployees":-1,"connectedCargoBayReferenceIDNew":"a1991072-e29c-4d70-872b-07249acfeedb"},{"referenceID":"09f9594b-d40f-4245-bf95-154f3074c785","position":{"x":474.5,"y":117.5,"z":0.0},"rotation":{"x":0.0,"y":0.0,"z":0.0,"w":1.0},"floor":0,"objectName":"","variationIndex":0,"objectSize":0,"objectQuality":0,"isActivated":true,"shouldBeActivated":true,"isInside":true,"isBuilt":true,"isMarkedForDemolish":false,"constructionInProgress":false,"deconstructionInProgress":false,"constructionEnergyAdded":1.0,"isPlanned":false,"condition":1.0,"isBroken":false,"isBeingRepaired":false,"cleanliness":1.0,"colors":[],"roomType":6,"businessReferenceID":"","allowAllBusinessesOfType":false,"attachedCountersReferenceIDs":[],"connectedCargoBayReferenceID":"","roomStartPos":{"x":467.0,"y":124.0},"roomEndPos":{"x":482.0,"y":111.0},"roomSize":{"x":16.0,"y":14.0},"allowedPerson":0,"allowedGender":0,"allowedWealthClass":0,"allowedEmployeeTypes":[],"hasCreatedJobTasks":false,"timeToRegenerateJobTasksString":"0001-01-01 20:07","nbrOfStationedEmployees":-1,"connectedCargoBayReferenceIDNew":"e496ab9a-9369-475d-8fbc-4406940a9b91"},{"referenceID":"125f1951-cc90-4361-ad70-172dd98142a2","position":{"x":298.5,"y":118.0,"z":0.0},"rotation":{"x":0.0,"y":0.0,"z":0.0,"w":1.0},"floor":0,"objectName":"","variationIndex":0,"objectSize":0,"objectQuality":0,"isActivated":true,"shouldBeActivated":true,"isInside":true,"isBuilt":true,"isMarkedForDemolish":false,"constructionInProgress":false,"deconstructionInProgress":false,"constructionEnergyAdded":1.0,"isPlanned":false,"condition":1.0,"isBroken":false,"isBeingRepaired":false,"cleanliness":1.0,"colors":[],"roomType":6,"businessReferenceID":"","allowAllBusinessesOfType":false,"attachedCountersReferenceIDs":[],"connectedCargoBayReferenceID":"","roomStartPos":{"x":291.0,"y":125.0},"roomEndPos":{"x":306.0,"y":111.0},"roomSize":{"x":16.0,"y":15.0},"allowedPerson":0,"allowedGender":0,"allowedWealthClass":0,"allowedEmployeeTypes":[],"hasCreatedJobTasks":false,"timeToRegenerateJobTasksString":"0001-01-01 20:07","nbrOfStationedEmployees":-1,"connectedCargoBayReferenceIDNew":"f9e0a563-8887-47c2-8929-21bbc54345a3"},{"referenceID":"9a5225a4-9471-4052-b2d0-b9fd86ce22dd","position":{"x":314.5,"y":118.0,"z":0.0},"rotation":{"x":0.0,"y":0.0,"z":0.0,"w":1.0},"floor":0,"objectName":"","variationIndex":0,"objectSize":0,"objectQuality":0,"isActivated":true,"shouldBeActivated":true,"isInside":true,"isBuilt":true,"isMarkedForDemolish":false,"constructionInProgress":false,"deconstructionInProgress":false,"constructionEnergyAdded":1.0,"isPlanned":false,"condition":1.0,"isBroken":false,"isBeingRepaired":false,"cleanliness":1.0,"colors":[],"roomType":6,"businessReferenceID":"","allowAllBusinessesOfType":false,"attachedCountersReferenceIDs":[],"connectedCargoBayReferenceID":"","roomStartPos":{"x":307.0,"y":125.0},"roomEndPos":{"x":322.0,"y":111.0},"roomSize":{"x":16.0,"y":15.0},"allowedPerson":0,"allowedGender":0,"allowedWealthClass":0,"allowedEmployeeTypes":[],"hasCreatedJobTasks":false,"timeToRegenerateJobTasksString":"0001-01-01 20:07","nbrOfStationedEmployees":-1,"connectedCargoBayReferenceIDNew":"d6281665-93b9-4585-9164-50c7590d0d25"},{"referenceID":"b00a205e-a49d-4ec6-b437-b48f1c05e3fa","position":{"x":330.5,"y":118.0,"z":0.0},"rotation":{"x":0.0,"y":0.0,"z":0.0,"w":1.0},"floor":0,"objectName":"","variationIndex":0,"objectSize":0,"objectQuality":0,"isActivated":true,"shouldBeActivated":true,"isInside":true,"isBuilt":true,"isMarkedForDemolish":false,"constructionInProgress":false,"deconstructionInProgress":false,"constructionEnergyAdded":1.0,"isPlanned":false,"condition":1.0,"isBroken":false,"isBeingRepaired":false,"cleanliness":1.0,"colors":[],"roomType":6,"businessReferenceID":"","allowAllBusinessesOfType":false,"attachedCountersReferenceIDs":[],"connectedCargoBayReferenceID":"","roomStartPos":{"x":323.0,"y":125.0},"roomEndPos":{"x":338.0,"y":111.0},"roomSize":{"x":16.0,"y":15.0},"allowedPerson":0,"allowedGender":0,"allowedWealthClass":0,"allowedEmployeeTypes":[],"hasCreatedJobTasks":false,"timeToRegenerateJobTasksString":"0001-01-01 20:07","nbrOfStationedEmployees":-1,"connectedCargoBayReferenceIDNew":"40d83b8e-ba7f-46d6-a113-29941ce42fde"}]}